mypy_nonfloat_decimal/__init__.py
mypy_nonfloat_decimal/mypy_nonfloat_decimal.py
mypy_nonfloat_decimal-0.1.8.dist-info/LICENSE
mypy_nonfloat_decimal-0.1.8.dist-info/METADATA
mypy_nonfloat_decimal-0.1.8.dist-info/WHEEL
mypy_nonfloat_decimal-0.1.8.dist-info/RECORD
