Metadata-Version: 2.3
Name: mypy-nonfloat-decimal
Version: 0.1.8
Summary: Mypy plugin to prevent passing float type to Decimal to avoid imprecisions.
License: MIT
Author: yedpodtrzitko
Author-email: yedpodtrzitko@gmail.com
Requires-Python: >3.9
Classifier: License :: OSI Approved :: MIT License
Classifier: Programming Language :: Python :: 3
Classifier: Programming Language :: Python :: 3.10
Classifier: Programming Language :: Python :: 3.11
Classifier: Programming Language :: Python :: 3.12
Classifier: Programming Language :: Python :: 3.13
Requires-Dist: mypy (>=0.720)
